odoo/addons/l10n_it_fatturapa_in/README.rst
odoo/addons/l10n_it_fatturapa_in/__init__.py
odoo/addons/l10n_it_fatturapa_in/__manifest__.py
odoo/addons/l10n_it_fatturapa_in/i18n/it.po
odoo/addons/l10n_it_fatturapa_in/i18n/l10n_it_fatturapa_in.pot
odoo/addons/l10n_it_fatturapa_in/migrations/12.0.1.15.0/post-migration.py
odoo/addons/l10n_it_fatturapa_in/migrations/12.0.1.18.3/pre-migration.py
odoo/addons/l10n_it_fatturapa_in/migrations/12.0.2.0.0/post-migration.py
odoo/addons/l10n_it_fatturapa_in/migrations/12.0.2.0.0/pre-migration.py
odoo/addons/l10n_it_fatturapa_in/models/__init__.py
odoo/addons/l10n_it_fatturapa_in/models/account.py
odoo/addons/l10n_it_fatturapa_in/models/attachment.py
odoo/addons/l10n_it_fatturapa_in/models/company.py
odoo/addons/l10n_it_fatturapa_in/models/partner.py
odoo/addons/l10n_it_fatturapa_in/readme/CONFIGURE.rst
odoo/addons/l10n_it_fatturapa_in/readme/CONTRIBUTORS.rst
odoo/addons/l10n_it_fatturapa_in/readme/DESCRIPTION.rst
odoo/addons/l10n_it_fatturapa_in/readme/INSTALL.rst
odoo/addons/l10n_it_fatturapa_in/readme/ROADMAP.rst
odoo/addons/l10n_it_fatturapa_in/readme/USAGE.rst
odoo/addons/l10n_it_fatturapa_in/security/ir.model.access.csv
odoo/addons/l10n_it_fatturapa_in/security/rules.xml
odoo/addons/l10n_it_fatturapa_in/static/description/icon.png
odoo/addons/l10n_it_fatturapa_in/static/description/index.html
odoo/addons/l10n_it_fatturapa_in/static/src/img/icon.png
odoo/addons/l10n_it_fatturapa_in/tests/__init__.py
odoo/addons/l10n_it_fatturapa_in/tests/fatturapa_common.py
odoo/addons/l10n_it_fatturapa_in/tests/test_import_fatturapa_xml.py
odoo/addons/l10n_it_fatturapa_in/tests/data/IT01234567890_FPR03.base64.xml.p7m
odoo/addons/l10n_it_fatturapa_in/tests/data/IT01234567890_FPR03.xml
odoo/addons/l10n_it_fatturapa_in/tests/data/IT01234567890_FPR03.xml.p7m
odoo/addons/l10n_it_fatturapa_in/tests/data/IT01234567890_FPR04.base64.xml.p7m
odoo/addons/l10n_it_fatturapa_in/tests/data/IT01234567890_FPR04.xml
odoo12_addon_l10n_it_fatturapa_in-12.0.3.1.10.dist-info/METADATA
odoo12_addon_l10n_it_fatturapa_in-12.0.3.1.10.dist-info/WHEEL
odoo12_addon_l10n_it_fatturapa_in-12.0.3.1.10.dist-info/top_level.txt
odoo12_addon_l10n_it_fatturapa_in-12.0.3.1.10.dist-info/RECORD
