Metadata-Version: 2.1
Name: odoo12-addon-l10n_it_fatturapa_in
Version: 12.0.3.1.10
Summary: Ricezione fatture elettroniche
Home-page: https://github.com/OCA/l10n-italy/tree/12.0/l10n_it_fatturapa_in
Author: Agile Business Group, Innoviu, Odoo Community Association (OCA)
Author-email: support@odoo-community.org
License: AGPL-3
Classifier: Programming Language :: Python
Classifier: Framework :: Odoo
Classifier: Framework :: Odoo :: 12.0
Classifier: License :: OSI Approved :: GNU Affero General Public License v3
Classifier: Development Status :: 4 - Beta
Requires-Python: >=3.5
Requires-Dist: odoo12-addon-base-vat-sanitized
Requires-Dist: odoo12-addon-l10n-it-fatturapa
Requires-Dist: odoo12-addon-l10n-it-withholding-tax-causali
Requires-Dist: odoo<12.1dev,>=12.0a
